nnf/__init__.py
nnf/__main__.py
nnf/amc.py
nnf/builders.py
nnf/cli.py
nnf/dimacs.py
nnf/dsharp.py
nnf/kissat.py
nnf/operators.py
nnf/py.typed
nnf/pysat.py
nnf/tseitin.py
nnf/util.py
nnf/bin/LICENSE.kissat
nnf/bin/README.md
nnf/bin/kissat
nnf-0.4.1.dist-info/LICENSE
nnf-0.4.1.dist-info/METADATA
nnf-0.4.1.dist-info/WHEEL
nnf-0.4.1.dist-info/entry_points.txt
nnf-0.4.1.dist-info/top_level.txt
nnf-0.4.1.dist-info/RECORD
