Metadata-Version: 2.1
Name: nnf
Version: 0.4.1
Summary: Manipulate NNF (Negation Normal Form) logical sentences
Home-page: https://github.com/QuMuLab/python-nnf
Author: Jan Verbeek, Christian Muise
Author-email: jan.verbeek@posteo.nl, christian.muise@queensu.ca
License: ISC
Project-URL: Documentation, https://python-nnf.readthedocs.io/
Project-URL: Source, https://github.com/QuMuLab/python-nnf
Keywords: logic nnf dimacs dsharp
Classifier: Intended Audience :: Science/Research
Classifier: Topic :: Scientific/Engineering
Classifier: Topic :: Scientific/Engineering :: Mathematics
Classifier: Development Status :: 4 - Beta
Classifier: Programming Language :: Python
Classifier: Programming Language :: Python :: 3
Classifier: Programming Language :: Python :: 3.4
Classifier: Programming Language :: Python :: 3.5
Classifier: Programming Language :: Python :: 3.6
Classifier: Programming Language :: Python :: 3.7
Classifier: Programming Language :: Python :: 3.8
Classifier: Programming Language :: Python :: 3 :: Only
Classifier: License :: OSI Approved :: ISC License (ISCL)
Requires-Python: >=3.4
Provides-Extra: pysat
License-File: LICENSE
